odoo/addons/fiscal_epos_print/README.rst
odoo/addons/fiscal_epos_print/__init__.py
odoo/addons/fiscal_epos_print/__manifest__.py
odoo/addons/fiscal_epos_print/i18n/fiscal_epos_print.pot
odoo/addons/fiscal_epos_print/i18n/it.po
odoo/addons/fiscal_epos_print/models/__init__.py
odoo/addons/fiscal_epos_print/models/account.py
odoo/addons/fiscal_epos_print/models/account_journal.py
odoo/addons/fiscal_epos_print/models/hr_employee.py
odoo/addons/fiscal_epos_print/models/hr_employee_base.py
odoo/addons/fiscal_epos_print/models/point_of_sale.py
odoo/addons/fiscal_epos_print/models/pos_order.py
odoo/addons/fiscal_epos_print/models/pos_payment.py
odoo/addons/fiscal_epos_print/models/pos_payment_method.py
odoo/addons/fiscal_epos_print/models/pos_session.py
odoo/addons/fiscal_epos_print/models/res_config_settings.py
odoo/addons/fiscal_epos_print/models/res_users.py
odoo/addons/fiscal_epos_print/readme/CONFIGURE.md
odoo/addons/fiscal_epos_print/readme/CONTRIBUTORS.md
odoo/addons/fiscal_epos_print/readme/DESCRIPTION.md
odoo/addons/fiscal_epos_print/readme/ROADMAP.md
odoo/addons/fiscal_epos_print/static/description/icon.png
odoo/addons/fiscal_epos_print/static/description/index.html
odoo/addons/fiscal_epos_print/static/lib/fiscalprint/fiscalprint.js
odoo/addons/fiscal_epos_print/static/lib/pikaday/pikaday.min.css
odoo/addons/fiscal_epos_print/static/lib/pikaday/pikaday.min.js
odoo/addons/fiscal_epos_print/static/src/css/pos.css
odoo/addons/fiscal_epos_print/static/src/css/pos_reprint.css
odoo/addons/fiscal_epos_print/static/src/img/X.svg
odoo/addons/fiscal_epos_print/static/src/img/Z.svg
odoo/addons/fiscal_epos_print/static/src/img/ade-logo.svg
odoo/addons/fiscal_epos_print/static/src/img/cashdrawer.svg
odoo/addons/fiscal_epos_print/static/src/img/epos.svg
odoo/addons/fiscal_epos_print/static/src/img/reprint.svg
odoo/addons/fiscal_epos_print/static/src/js/epson_epos_print.js
odoo/addons/fiscal_epos_print/static/src/js/models.js
odoo_addon_fiscal_epos_print-16.0.1.0.1.dist-info/METADATA
odoo_addon_fiscal_epos_print-16.0.1.0.1.dist-info/WHEEL
odoo_addon_fiscal_epos_print-16.0.1.0.1.dist-info/top_level.txt
odoo_addon_fiscal_epos_print-16.0.1.0.1.dist-info/RECORD
