Metadata-Version: 2.1
Name: odoo-addon-fiscal_epos_print
Version: 16.0.1.0.1
Requires-Python: >=3.10
Requires-Dist: odoo>=16.0a,<16.1dev
Summary: ePOS-Print XML Fiscal Printer Driver - Stampanti Epson compatibili: FP81II, FP90III
Home-page: https://github.com/OCA/l10n-italy
License: AGPL-3
Author: Odoo Community Association (OCA), Agile Business Group, Leonardo Donelli, TAKOBI, Level Prime Srl
Author-email: support@odoo-community.org
Classifier: Programming Language :: Python
Classifier: Framework :: Odoo
Classifier: Framework :: Odoo :: 16.0
Classifier: License :: OSI Approved :: GNU Affero General Public License v3
